vision_gui.py
vision_run.py
visionlite/__init__.py
visionlite/_st_app.py
visionlite/_tree_variations.py
visionlite/_vision_ai.py
visionlite/latest_st_app.py
visionlite/main.py
visionlite/wordllama_rag_tree/__init__.py
visionlite/wordllama_rag_tree/_main.py
visionlite/wordllama_rag_tree/_retriever.py
visionlite/wordllama_rag_tree/_sentvar.py
visionlite-0.1.60.dist-info/LICENSE
visionlite-0.1.60.dist-info/METADATA
visionlite-0.1.60.dist-info/WHEEL
visionlite-0.1.60.dist-info/entry_points.txt
visionlite-0.1.60.dist-info/RECORD
